mpo/__init__.py
mpo/category.py
mpo/coupon.py
mpo/order.py
mpo/pricelist.py
mpo/product.py
mpo/tax.py
mpo/version.py
mpo-0.1.4.dist-info/LICENSE
mpo-0.1.4.dist-info/METADATA
mpo-0.1.4.dist-info/WHEEL
mpo-0.1.4.dist-info/top_level.txt
mpo-0.1.4.dist-info/RECORD
