Metadata-Version: 2.1
Name: mpo
Version: 0.1.4
Summary: MPO is a library for Python to map models between PrestaShop and odoo .
Home-page: https://github.com/AISYSNEXT-Ltd/mpo
Author: Aymen Jemi <jemiaymen@gmail.com> (AISYSNEXT)
Author-email: jemiaymen@gmail.com
License: GNU GPL-3
Keywords: prestashop,e-com,e-commerce,prestashop api,api,webservice,mapper,odoo
Classifier: Programming Language :: Python
Classifier: Programming Language :: Python :: 3.11
Classifier: Programming Language :: Python :: 3.10
Classifier: Programming Language :: Python :: 3.9
Classifier: Programming Language :: Python :: 3.8
Classifier: Development Status :: 4 - Beta
Classifier: Intended Audience :: Developers
Classifier: Topic :: Software Development :: Libraries :: Python Modules
Classifier: Topic :: Internet :: WWW/HTTP :: Site Management
Classifier: Topic :: Internet
License-File: LICENSE
Requires-Dist: cleantxt
